Workbook

Sheet Assumptions
A1: D&D Invoice Defense — Cash-Flow Model (Assumptions)
A2: Blue = inputs you change. Black = calculated. Built June 2026.
A4: PRICING — monthly subscription ($)
A5: Starter (≤50 invoices/mo) | B5: 149
A6: Growth (≤250 invoices/mo) | B6: 399
A7: Pro (≤1,000 invoices/mo) | B7: 899
A8: Managed add-on | B8: 750 | C8: optional service tier
A10: CUSTOMER MIX — share of customers on each tier
A11: Starter % | B11: 0.6
A12: Growth % | B12: 0.3
A13: Pro % | B13: 0.1
A14: Managed attach % (of all customers) | B14: 0.05
A15: Mix check (must = 100%) | B15: =B11+B12+B13
A16: Blended ARPU ($/customer/mo) | B16: =B11*B5+B12*B6+B13*B7+B14*B8
A18: UNIT ECONOMICS (cost to serve)
A19: API cost per invoice ($) | B19: 0.03 | C19: Haiku vision extraction
A20: Avg invoices / customer / mo | B20: 150
A21: API cost / customer / mo ($) | B21: =B19*B20
A23: OPERATING COSTS — monthly ($)
A24: Infrastructure (hosting, domain) | B24: 50 | C24: Railway + misc
A25: Founder draw (your salary) | B25: 0 | C25: set >0 to pay yourself
A27: RETENTION
A28: Monthly churn rate | B28: 0.04 | C28: % of customers lost/mo

Sheet Monthly Model
A1: Monthly Cash Flow — base case (Jul 2026 → Dec 2028)
A3: Month | B3: New Customers | C3: Churned | D3: Ending Customers | E3: Revenue ($) | F3: API Cost ($) | G3: Gross Profit ($) | H3: Operating Costs ($) | I3: Net Cash Flow ($) | J3: Cumulative Cash ($)
A4: Jul-26 | B4: 0 | C4: 0 | D4: =B4-C4 | E4: =D4*Assumptions!$B$16 | F4: =D4*Assumptions!$B$21 | G4: =E4-F4 | H4: =Assumptions!$B$24+Assumptions!$B$25 | I4: =G4-H4 | J4: =I4
A5: Aug-26 | B5: 1 | C5: =ROUND(D4*Assumptions!$B$28,0) | D5: =D4+B5-C5 | E5: =D5*Assumptions!$B$16 | F5: =D5*Assumptions!$B$21 | G5: =E5-F5 | H5: =Assumptions!$B$24+Assumptions!$B$25 | I5: =G5-H5 | J5: =I5+J4
A6: Sep-26 | B6: 1 | C6: =ROUND(D5*Assumptions!$B$28,0) | D6: =D5+B6-C6 | E6: =D6*Assumptions!$B$16 | F6: =D6*Assumptions!$B$21 | G6: =E6-F6 | H6: =Assumptions!$B$24+Assumptions!$B$25 | I6: =G6-H6 | J6: =I6+J5
A7: Oct-26 | B7: 2 | C7: =ROUND(D6*Assumptions!$B$28,0) | D7: =D6+B7-C7 | E7: =D7*Assumptions!$B$16 | F7: =D7*Assumptions!$B$21 | G7: =E7-F7 | H7: =Assumptions!$B$24+Assumptions!$B$25 | I7: =G7-H7 | J7: =I7+J6
A8: Nov-26 | B8: 2 | C8: =ROUND(D7*Assumptions!$B$28,0) | D8: =D7+B8-C8 | E8: =D8*Assumptions!$B$16 | F8: =D8*Assumptions!$B$21 | G8: =E8-F8 | H8: =Assumptions!$B$24+Assumptions!$B$25 | I8: =G8-H8 | J8: =I8+J7
A9: Dec-26 | B9: 3 | C9: =ROUND(D8*Assumptions!$B$28,0) | D9: =D8+B9-C9 | E9: =D9*Assumptions!$B$16 | F9: =D9*Assumptions!$B$21 | G9: =E9-F9 | H9: =Assumptions!$B$24+Assumptions!$B$25 | I9: =G9-H9 | J9: =I9+J8
A10: Jan-27 | B10: 3 | C10: =ROUND(D9*Assumptions!$B$28,0) | D10: =D9+B10-C10 | E10: =D10*Assumptions!$B$16 | F10: =D10*Assumptions!$B$21 | G10: =E10-F10 | H10: =Assumptions!$B$24+Assumptions!$B$25 | I10: =G10-H10 | J10: =I10+J9
A11: Feb-27 | B11: 3 | C11: =ROUND(D10*Assumptions!$B$28,0) | D11: =D10+B11-C11 | E11: =D11*Assumptions!$B$16 | F11: =D11*Assumptions!$B$21 | G11: =E11-F11 | H11: =Assumptions!$B$24+Assumptions!$B$25 | I11: =G11-H11 | J11: =I11+J10
A12: Mar-27 | B12: 4 | C12: =ROUND(D11*Assumptions!$B$28,0) | D12: =D11+B12-C12 | E12: =D12*Assumptions!$B$16 | F12: =D12*Assumptions!$B$21 | G12: =E12-F12 | H12: =Assumptions!$B$24+Assumptions!$B$25 | I12: =G12-H12 | J12: =I12+J11
A13: Apr-27 | B13: 4 | C13: =ROUND(D12*Assumptions!$B$28,0) | D13: =D12+B13-C13 | E13: =D13*Assumptions!$B$16 | F13: =D13*Assumptions!$B$21 | G13: =E13-F13 | H13: =Assumptions!$B$24+Assumptions!$B$25 | I13: =G13-H13 | J13: =I13+J12
A14: May-27 | B14: 4 | C14: =ROUND(D13*Assumptions!$B$28,0) | D14: =D13+B14-C14 | E14: =D14*Assumptions!$B$16 | F14: =D14*Assumptions!$B$21 | G14: =E14-F14 | H14: =Assumptions!$B$24+Assumptions!$B$25 | I14: =G14-H14 | J14: =I14+J13
A15: Jun-27 | B15: 5 | C15: =ROUND(D14*Assumptions!$B$28,0) | D15: =D14+B15-C15 | E15: =D15*Assumptions!$B$16 | F15: =D15*Assumptions!$B$21 | G15: =E15-F15 | H15: =Assumptions!$B$24+Assumptions!$B$25 | I15: =G15-H15 | J15: =I15+J14
A16: Jul-27 | B16: 5 | C16: =ROUND(D15*Assumptions!$B$28,0) | D16: =D15+B16-C16 | E16: =D16*Assumptions!$B$16 | F16: =D16*Assumptions!$B$21 | G16: =E16-F16 | H16: =Assumptions!$B$24+Assumptions!$B$25 | I16: =G16-H16 | J16: =I16+J15
... A33: Dec-28 | B33: 8 | C33: =ROUND(D32*Assumptions!$B$28,0) | D33: =D32+B33-C33 | E33: =D33*Assumptions!$B$16 | F33: =D33*Assumptions!$B$21 | G33: =E33-F33 | H33: =Assumptions!$B$24+Assumptions!$B$25 | I33: =G33-H33 | J33: =I33+J32

Sheet Annual Summary
A1: Annual Summary & Scenarios
B3: 2026 (H2) | C3: 2027 | D3: 2028
A4: New customers added | B4: =SUM('Monthly Model'!B4:B9) | C4: =SUM('Monthly Model'!B10:B21) | D4: =SUM('Monthly Model'!B22:B33)
A5: Revenue | B5: =SUM('Monthly Model'!E4:E9) | C5: =SUM('Monthly Model'!E10:E21) | D5: =SUM('Monthly Model'!E22:E33)
A6: API cost | B6: =SUM('Monthly Model'!F4:F9) | C6: =SUM('Monthly Model'!F10:F21) | D6: =SUM('Monthly Model'!F22:F33)
A7: Gross profit | B7: =SUM('Monthly Model'!G4:G9) | C7: =SUM('Monthly Model'!G10:G21) | D7: =SUM('Monthly Model'!G22:G33)
A8: Operating costs | B8: =SUM('Monthly Model'!H4:H9) | C8: =SUM('Monthly Model'!H10:H21) | D8: =SUM('Monthly Model'!H22:H33)
A9: Net cash flow | B9: =SUM('Monthly Model'!I4:I9) | C9: =SUM('Monthly Model'!I10:I21) | D9: =SUM('Monthly Model'!I22:I33)
A10: Ending customers (year-end) | B10: ='Monthly Model'!D9 | C10: ='Monthly Model'!D21 | D10: ='Monthly Model'!D33
A11: ARR run-rate (year-end, $) | B11: ='Monthly Model'!E9*12 | C11: ='Monthly Model'!E21*12 | D11: ='Monthly Model'!E33*12
A12: Gross margin % | B12: =(B5-B6)/B5 | C12: =(C5-C6)/C5 | D12: =(D5-D6)/D5
A14: SCENARIO SENSITIVITY — 2027 revenue
A15: Customer acquisition vs. base plan
A16: Scenario | B16: Multiplier | C16: 2027 Revenue | D16: 2027 Net Cash
A17: Conservative (60% of plan) | B17: 0.6 | C17: =$C$5*B17 | D17: =$C$9*B17
A18: Base plan | B18: 1 | C18: =$C$5*B18 | D18: =$C$9*B18
A19: Aggressive (160% of plan) | B19: 1.6 | C19: =$C$5*B19 | D19: =$C$9*B19
A21: HOW TO USE: change any blue/yellow cell. The main lever is the 'New Customers' column on the Monthly Model tab,
A22: and pricing/mix/churn on the Assumptions tab. Everything else recalculates.
A24: READING IT: Revenue is ~98% gross margin because each audit costs pennies (one cheap extraction call).
A25: The real constraint is NOT money — it's customer acquisition and your time. Founder draw is set to $0;
A26: raise it on the Assumptions tab to model paying yourself.
A28: Base case: ~$7k revenue in H2 2026, ~$125k in 2027 (exit ~$17k MRR / ~$210k ARR run-rate), scaling through 2028.
A29: These are STARTING ASSUMPTIONS to validate with real customers — not a forecast. Reality will be lumpier.
